README.md
license.txt
setup.py
Testando_o_c_digo_para_Ensalamento.egg-info/PKG-INFO
Testando_o_c_digo_para_Ensalamento.egg-info/SOURCES.txt
Testando_o_c_digo_para_Ensalamento.egg-info/dependency_links.txt
Testando_o_c_digo_para_Ensalamento.egg-info/top_level.txt
pro_video_ferramentas/__init__.py
pro_video_ferramentas/camera.py
pro_video_ferramentas/video.py