Metadata-Version: 2.1
Name: Testando-o-c-digo-para-Ensalamento
Version: 1.0
Summary: Ferramenta em teste
Author: Flavio
Author-email: professorflaviosoares@gmail.com
License-File: license.txt
